spondee/__init__.py
spondee/numeric.py
spondee/schemas.py
spondee/search.py
spondee-0.1.3.dist-info/LICENSE
spondee-0.1.3.dist-info/METADATA
spondee-0.1.3.dist-info/WHEEL
spondee-0.1.3.dist-info/RECORD
