Metadata-Version: 2.1
Name: spondee
Version: 0.1.3
Summary: Sentence algorithms for Stanza
License: MIT
Author: tbonza
Author-email: tylers.pile@gmail.com
Requires-Python: >=3.10,<3.13
Classifier: License :: OSI Approved :: MIT License
Classifier: Programming Language :: Python :: 3
Classifier: Programming Language :: Python :: 3.10
Classifier: Programming Language :: Python :: 3.11
Classifier: Programming Language :: Python :: 3.12
Requires-Dist: networkx (>=3.3,<4.0)
Requires-Dist: numpy (<2.0.0)
Requires-Dist: pydantic (>=2.7.3,<3.0.0)
Requires-Dist: stanza (>=1.8.2,<2.0.0)
Requires-Dist: torch (>=2.2,<2.3)
